brainfy/__init__.py
brainfy/__main__.py
brainfy/interpreter.py
brainfy/parser.py
brainfy/tokenizer.py
brainfy/traceback.py
brainfy-0.1.4.dist-info/LICENSE
brainfy-0.1.4.dist-info/METADATA
brainfy-0.1.4.dist-info/WHEEL
brainfy-0.1.4.dist-info/entry_points.txt
brainfy-0.1.4.dist-info/RECORD
