Metadata-Version: 2.1
Name: brainfy
Version: 0.1.4
Summary: Interpreter for the esoteric language brainf*ck written in Python.
License: MIT
Author: Lelzin λ
Author-email: d3cryptofc@gmail.com
Requires-Python: >=3.8,<4.0
Classifier: License :: OSI Approved :: MIT License
Classifier: Programming Language :: Python :: 3
Classifier: Programming Language :: Python :: 3.8
Classifier: Programming Language :: Python :: 3.9
Classifier: Programming Language :: Python :: 3.10
Classifier: Programming Language :: Python :: 3.11
Classifier: Programming Language :: Python :: 3.12
Project-URL: Repository, https://github.com/d3cryptofc/brainfy
